{
  "INNOVATION_DESCRIPTION": {
    "innovationFields": ["description", "hasFinalProduct", "otherCategoryDescription", "mainPurpose"],
    "innovationTypes": ["categories", "areas", "clinicalAreas", "careSettings"]
  },
  "VALUE_PROPOSITION": {
    "innovationFields": ["problemsTackled", "problemsConsequences", "intervention", "interventionImpact"]
  },
  "UNDERSTANDING_OF_NEEDS": {
    "innovationFields": ["hasSubgroups"],
    "innovationDependencies": [
      {
        "type": "subgroups",
        "fields": ["name", "conditions"]
      }
    ]
  },
  "UNDERSTANDING_OF_BENEFITS": {
    "innovationFields": ["hasBenefits", "benefits"],
    "innovationDependencies": [
      {
        "type": "subgroups",
        "fields": ["benefits"]
      }
    ]
  },
  "EVIDENCE_OF_EFFECTIVENESS": {
    "innovationFields": ["hasEvidence"]
  },
  "MARKET_RESEARCH": {
    "innovationFields": ["marketResearch", "hasMarketResearch"]
  },
  "INTELLECTUAL_PROPERTY": {
    "innovationFields": ["hasPatents", "hasOtherIntellectual", "otherIntellectual"]
  },
  "REGULATIONS_AND_STANDARDS": {
    "innovationFields": ["hasRegulationKnowledge", "otherRegulationDescription"],
    "innovationDependencies": [
      {
        "type": "standards",
        "fields": ["type", "hasMet"]
      }
    ],
    "files": true
  },
  "CURRENT_CARE_PATHWAY": {
    "innovationFields": ["hasUKPathwayKnowledge", "innovationPathwayKnowledge", "potentialPathway"],
    "innovationDependencies": [
      {
        "type": "subgroups",
        "fields": ["carePathway"]
      }
    ]
  },
  "TESTING_WITH_USERS": {
    "innovationFields": ["hasTests"],
    "innovationDependencies": [
      {
        "type": "userTests",
        "fields": ["kind", "feedback"]
      }
    ],
    "files": true
  },
  "COST_OF_INNOVATION": {
    "innovationFields": ["hasCostKnowledge"],
    "innovationDependencies": [
      {
        "type": "subgroups",
        "fields": ["costDescription", "patientsRange", "sellExpectations", "usageExpectations"]
      }
    ]
  },
  "COMPARATIVE_COST_BENEFIT": {
    "innovationFields": ["hasCostSavingKnowledge", "hasCostCareKnowledge"],
    "innovationDependencies": [
      {
        "type": "subgroups",
        "fields": ["costComparison"]
      }
    ]
  },
  "REVENUE_MODEL": {
    "innovationFields": ["hasRevenueModel", "payingOrganisations", "benefittingOrganisations", "hasFunding", "fundingDescription", "otherRevenueDescription"],
    "innovationTypes": ["revenues"]
  },
  "IMPLEMENTATION_PLAN": {
    "innovationFields": ["hasDeployPlan", "isDeployed", "hasResourcesToScale"],
    "innovationDependencies": [
      {
        "type": "deploymentPlans",
        "fields": ["name", "commercialBasis", "orgDeploymentAffect"]
      }
    ],
    "files": true
  }
}